AUTHORS.rst
CONTRIBUTING.rst
HISTORY.rst
LICENSE.rst
MANIFEST.in
README.rst
setup.cfg
setup.py
respect/__init__.py
respect/dispatch.py
respect/exceptions.py
respect/main.py
respect/spelling.py
respect/utils.py
respect.egg-info/PKG-INFO
respect.egg-info/SOURCES.txt
respect.egg-info/dependency_links.txt
respect.egg-info/entry_points.txt
respect.egg-info/not-zip-safe
respect.egg-info/requires.txt
respect.egg-info/top_level.txt