Metadata-Version: 1.1
Name: respect
Version: 0.1.0
Summary: A command-line tool to interact with the Github API.         Getting to know software developers you Respect.
Home-page: https://github.com/oubiga/respect
Author: Pablo Oubiña
Author-email: oubiga@yahoo.es
License: BSD
Keywords: respect github repository stars user code software command
Platform: UNKNOWN
Classifier: Development Status :: 1 - Planning
Classifier: Topic :: Utilities
Classifier: Environment :: Console
Classifier: Intended Audience :: Developers
Classifier: Natural Language :: English
Classifier: License :: OSI Approved :: BSD License
Classifier: Programming Language :: Python
Classifier: Programming Language :: Python :: 2
Classifier: Programming Language :: Python :: 2.6
Classifier: Programming Language :: Python :: 2.7
Classifier: Programming Language :: Python :: 3
Classifier: Programming Language :: Python :: 3.3
